vapiserve/__init__.py
vapiserve/cli.py
vapiserve/core/__init__.py
vapiserve/core/models.py
vapiserve/core/server.py
vapiserve/core/tool.py
vapiserve/integrations/__init__.py
vapiserve/integrations/ai/__init__.py
vapiserve/integrations/ai/base.py
vapiserve/integrations/ai/openai.py
vapiserve/integrations/communication/__init__.py
vapiserve/integrations/communication/base.py
vapiserve/integrations/communication/slack.py
vapiserve/integrations/crm/__init__.py
vapiserve/integrations/crm/base.py
vapiserve/integrations/crm/hubspot.py
vapiserve/integrations/email/__init__.py
vapiserve/integrations/email/base.py
vapiserve/integrations/email/sendgrid.py
vapiserve/integrations/scheduling/__init__.py
vapiserve/integrations/scheduling/base.py
vapiserve/integrations/scheduling/cal_com.py
vapiserve/integrations/scheduling/google_calendar.py
vapiserve/integrations/scheduling/outlook_calendar.py
vapiserve/integrations/storage/__init__.py
vapiserve/integrations/storage/aws_s3.py
vapiserve/integrations/storage/base.py
vapiserve/integrations/storage/google_cloud_storage.py
vapiserve/integrations/tasks/__init__.py
vapiserve/integrations/tasks/base.py
vapiserve/integrations/tasks/todoist.py
vapiserve/tools/__init__.py
vapiserve/tools/ai.py
vapiserve/tools/calendar.py
vapiserve/tools/storage.py
vapiserve/utils/__init__.py
vapiserve/utils/ngrok.py
vapiserve/utils/security.py
vapiserve-0.0.5.dist-info/METADATA
vapiserve-0.0.5.dist-info/WHEEL
vapiserve-0.0.5.dist-info/entry_points.txt
vapiserve-0.0.5.dist-info/licenses/LICENSE
vapiserve-0.0.5.dist-info/RECORD
