Metadata-Version: 2.4
Name: vapiserve
Version: 0.0.5
Summary: A framework for building API servers for Vapi custom tools with integrated service providers
Project-URL: Homepage, https://github.com/mahimairaja/vapiserve
Project-URL: Bug Tracker, https://github.com/mahimairaja/vapiserve/issues
Project-URL: Documentation, https://mahimairaja.github.io/vapiserve
Author-email: Mahimai Raja <mahimairaja3@gmail.com>
License: MIT License
License-File: LICENSE
Classifier: Development Status :: 3 - Alpha
Classifier: Intended Audience :: Developers
Classifier: License :: OSI Approved :: MIT License
Classifier: Programming Language :: Python :: 3
Classifier: Programming Language :: Python :: 3.8
Classifier: Programming Language :: Python :: 3.9
Classifier: Programming Language :: Python :: 3.10
Classifier: Programming Language :: Python :: 3.11
Requires-Python: >=3.8
Requires-Dist: fastapi>=0.100.0
Requires-Dist: httpx>=0.24.0
Requires-Dist: pydantic>=2.0.0
Requires-Dist: python-dotenv>=1.0.0
Requires-Dist: requests>=2.28.0
Requires-Dist: uvicorn>=0.22.0
Provides-Extra: ai
Requires-Dist: anthropic>=0.5.0; extra == 'ai'
Requires-Dist: openai>=0.27.8; extra == 'ai'
Provides-Extra: all-integrations
Requires-Dist: anthropic>=0.5.0; extra == 'all-integrations'
Requires-Dist: boto3>=1.26.0; extra == 'all-integrations'
Requires-Dist: google-api-python-client>=2.97.0; extra == 'all-integrations'
Requires-Dist: google-auth>=2.22.0; extra == 'all-integrations'
Requires-Dist: google-cloud-storage>=2.8.0; extra == 'all-integrations'
Requires-Dist: microsoft-graph-core>=0.0.1; extra == 'all-integrations'
Requires-Dist: msal>=1.20.0; extra == 'all-integrations'
Requires-Dist: openai>=0.27.8; extra == 'all-integrations'
Requires-Dist: sendgrid>=6.0.0; extra == 'all-integrations'
Requires-Dist: slack-sdk>=3.21.3; extra == 'all-integrations'
Requires-Dist: todoist-api-python>=2.0.0; extra == 'all-integrations'
Requires-Dist: twilio>=8.5.0; extra == 'all-integrations'
Provides-Extra: communication
Requires-Dist: slack-sdk>=3.21.3; extra == 'communication'
Requires-Dist: twilio>=8.5.0; extra == 'communication'
Provides-Extra: dev
Requires-Dist: black; extra == 'dev'
Requires-Dist: isort; extra == 'dev'
Requires-Dist: mypy; extra == 'dev'
Requires-Dist: pytest; extra == 'dev'
Requires-Dist: pytest-cov; extra == 'dev'
Requires-Dist: ruff; extra == 'dev'
Provides-Extra: email
Requires-Dist: sendgrid>=6.0.0; extra == 'email'
Provides-Extra: ngrok
Requires-Dist: pyngrok>=5.2.1; extra == 'ngrok'
Provides-Extra: scheduling
Requires-Dist: google-api-python-client>=2.97.0; extra == 'scheduling'
Requires-Dist: google-auth>=2.22.0; extra == 'scheduling'
Requires-Dist: microsoft-graph-core>=0.0.1; extra == 'scheduling'
Requires-Dist: msal>=1.20.0; extra == 'scheduling'
Provides-Extra: storage
Requires-Dist: boto3>=1.26.0; extra == 'storage'
Requires-Dist: google-cloud-storage>=2.8.0; extra == 'storage'
Provides-Extra: tasks
Requires-Dist: todoist-api-python>=2.0.0; extra == 'tasks'
